secure_cookie/__init__.py
secure_cookie/_compat.py
secure_cookie/cookie.py
secure_cookie/session.py
secure_cookie-0.2.0.dist-info/LICENSE.rst
secure_cookie-0.2.0.dist-info/METADATA
secure_cookie-0.2.0.dist-info/WHEEL
secure_cookie-0.2.0.dist-info/top_level.txt
secure_cookie-0.2.0.dist-info/RECORD
