Metadata-Version: 2.1
Name: secure-cookie
Version: 0.2.0
Summary: Secure cookie and session interface for WSGI applications.
Home-page: https://secure-cookie.readthedocs.io/
Maintainer: Pallets
Maintainer-email: contact@palletsprojects.com
License: BSD-3-Clause
Project-URL: Documentation, https://secure-cookie.readthedocs.io/
Project-URL: Code, https://github.com/pallets/secure-cookie
Project-URL: Issue tracker, https://github.com/pallets/secure-cookie/issues
Platform: UNKNOWN
Classifier: Development Status :: 5 - Production/Stable
Classifier: Environment :: Web Environment
Classifier: Intended Audience :: Developers
Classifier: License :: OSI Approved :: BSD License
Classifier: Operating System :: OS Independent
Classifier: Programming Language :: Python
Classifier: Topic :: Internet :: WWW/HTTP
Classifier: Topic :: Internet :: WWW/HTTP :: Session
Classifier: Topic :: Internet :: WWW/HTTP :: WSGI
Classifier: Topic :: Internet :: WWW/HTTP :: WSGI :: Middleware
Requires-Python: >=3.6
License-File: LICENSE.rst
Requires-Dist: Werkzeug (>0.15)
